H2MM_C.cpython-39-x86_64-linux-gnu.so
H2MM_C/C_H2MM.h
H2MM_C/C_H2MM_txtread.c
H2MM_C/H2MM_C.c
H2MM_C/H2MM_C.pyx
H2MM_C/burst_threads.c
H2MM_C/fwd_back.c
H2MM_C/h2mm_functions.c
H2MM_C/model_array.c
H2MM_C/model_limits_funcs.c
H2MM_C/pathloglik.c
H2MM_C/rho_calc.c
H2MM_C/state_path.c
H2MM_C/test_H2MM_C.c
H2MM_C/test_h2mm_array.c
H2MM_C/test_h2mm_array_gamma.c
H2MM_C/test_h2mm_basic.c
H2MM_C/test_h2mm_gamma.c
H2MM_C/test_model_array.c
H2MM_C/test_model_array_gamma.c
H2MM_C/test_viterbi.c
H2MM_C/utils.c
H2MM_C/viterbi.c
h2mm_c-2.1.2.dist-info/METADATA
h2mm_c-2.1.2.dist-info/WHEEL
h2mm_c-2.1.2.dist-info/top_level.txt
h2mm_c-2.1.2.dist-info/RECORD
h2mm_c-2.1.2.dist-info/licenses/LICENSE.txt
