Metadata-Version: 2.1
Name: H2MM_C
Version: 2.1.2
Summary: C level implementation of H2MM algorithm by Pirchi. 2016
Author-email: Paul David Harris <harripd@gmail.com>
License: MIT
Project-URL: Homepage, https://github.com/harripd/H2MMpythonlib
Project-URL: Documentation, https://h2mmpythonlib.readthedocs.io/en/latest/
Project-URL: Repositories, https://github.com/harripd/H2MMpythonlib/
Project-URL: Issues, https://github.com/harripd/H2MMpythonlib/issues
Keywords: single-molecule FRET,smFRET,hidden markov model
Classifier: Intended Audience :: Science/Research
Classifier: Operating System :: OS Independent
Classifier: Programming Language :: Python :: 3.7
Classifier: Programming Language :: Python :: 3.8
Classifier: Programming Language :: Python :: 3.9
Classifier: Programming Language :: Python :: 3.10
Classifier: Programming Language :: Python :: 3.11
Classifier: Programming Language :: Python :: 3.12
Classifier: Programming Language :: Python :: 3.13
Classifier: Programming Language :: Python :: 3.14
Classifier: Programming Language :: Cython
Classifier: Programming Language :: C
Classifier: Topic :: Scientific/Engineering
Requires-Python: >=3.7
License-File: LICENSE.txt
Requires-Dist: numpy
Requires-Dist: IPython
Requires-Dist: importlib-metadata; python_version < "3.8"
